{
  "parent": "minecraft:recipes/root",
  "criteria": {
    "has_glowstone": {
      "conditions": {
        "items": [
          {
            "items": [
              "minecraft:glowstone"
            ]
          }
        ]
      },
      "trigger": "minecraft:inventory_changed"
    },
    "has_the_recipe": {
      "conditions": {
        "recipe": "softerpastels:white_light"
      },
      "trigger": "minecraft:recipe_unlocked"
    },
    "has_white_light": {
      "conditions": {
        "items": [
          {
            "items": [
              "softerpastels:white_light"
            ]
          }
        ]
      },
      "trigger": "minecraft:inventory_changed"
    },
    "has_white_powder": {
      "conditions": {
        "items": [
          {
            "items": [
              "softerpastels:white_powder"
            ]
          }
        ]
      },
      "trigger": "minecraft:inventory_changed"
    }
  },
  "requirements": [
    [
      "has_the_recipe",
      "has_glowstone",
      "has_white_powder",
      "has_white_light"
    ]
  ],
  "rewards": {
    "recipes": [
      "softerpastels:white_light"
    ]
  }
}